{
  "ok": false,
  "source": "Cloud MQTT",
  "timestamp": "2026-07-20T12:56:35",
  "error": "EcoFlow API error 8521: signature is wrong",
  "history": [],
  "telemetry": {
    "window": "24h",
    "sample_count": 13,
    "from": "2026-07-19T16:05:51",
    "to": "2026-07-20T11:18:17",
    "latest": {
      "mode": "idle",
      "grid": true,
      "soc": 74.0,
      "ac_v": 223.562,
      "in_w": 0.0,
      "out_w": 0.0,
      "charge_limit_w": 1800.0
    },
    "voltage": {
      "min": {
        "value": 223.0,
        "ts": "2026-07-19T16:05:51"
      },
      "max": {
        "value": 229.8,
        "ts": "2026-07-20T08:42:44"
      },
      "frequency_min": {
        "value": 50.0,
        "ts": "2026-07-19T16:05:51"
      },
      "frequency_max": {
        "value": 50.0,
        "ts": "2026-07-19T16:05:51"
      }
    },
    "soc": {
      "min": {
        "value": 74.0,
        "ts": "2026-07-20T09:32:27"
      },
      "max": {
        "value": 75.0,
        "ts": "2026-07-19T16:05:51"
      }
    },
    "power": {
      "max_load": {
        "value": 0.0,
        "ts": "2026-07-19T16:05:51"
      },
      "max_input": {
        "value": 0.0,
        "ts": "2026-07-19T16:05:51"
      },
      "max_ac_output": {
        "value": 0.0,
        "ts": "2026-07-19T16:05:51"
      },
      "charge_limit_w": 1800.0,
      "max_input_pct_of_current_limit": 0,
      "input_wh_est": 0.0,
      "load_wh_est": 0.0
    },
    "modes": {
      "charging_sec": 0,
      "discharging_sec": 0,
      "idle_sec": 1578,
      "charging": "0 сек",
      "discharging": "0 сек",
      "idle": "26 хв",
      "last_charging": null,
      "last_discharging": null
    }
  }
}